{"name": "Guárico", "id": 1139355, "predecessors": [{"name": "Entidades_subnacionales", "id": 365760}], "successors": [{"name": "Municipios_del_estado_Guárico", "id": 691041}, {"name": "Guariqueños", "id": 1147292}, {"name": "Historia_de_Guárico", "id": 6435038}, {"name": "Edificios_y_estructuras_de_Calabozo", "id": 6623522}, {"name": "Localidades_del_estado_Guárico", "id": 254297}, {"name": "Montañas_de_Guárico", "id": 7010736}, {"name": "Río_Orinoco", "id": 4544106}, {"name": "Gobernadores_de_Guárico", "id": 4819111}]}