{"name": "Historia_militar_de_Alemania", "id": 1212126, "predecessors": [{"name": "Fuerzas_armadas", "id": 68565}, {"name": "Historia_de_Alemania", "id": 58738}], "successors": [{"name": "Militarismo_alemán", "id": 253787}, {"name": "Imperio_alemán_en_la_Primera_Guerra_Mundial", "id": 5159837}, {"name": "Heer_(Wehrmacht)", "id": 6478134}, {"name": "Submarinos_Alemanes_de_la_Segunda_Guerra_Mundial", "id": 10321530}, {"name": "Wehrmacht", "id": 550665}, {"name": "Buques_de_guerra_de_Alemania_en_la_Primera_Guerra_Mundial", "id": 4603513}, {"name": "Batalla_de_Jutlandia", "id": 6533630}, {"name": "Submarinos_de_Alemania", "id": 1771994}, {"name": "Cruceros_de_la_Kaiserliche_Marine", "id": 1255539}, {"name": "Batallas_de_Prusia", "id": 736431}, {"name": "Batallas_de_la_Alemania_nazi", "id": 4187533}, {"name": "Batallas_del_Imperio_alemán_en_la_Primera_Guerra_Mundial", "id": 5276356}, {"name": "Unidades_militares_alemanas_de_la_Segunda_Guerra_Mundial", "id": 2050230}]}