{"name": "Equipos_de_fútbol_de_Inglaterra", "id": 131088, "predecessors": [{"name": "Fútbol_en_Inglaterra", "id": 4169829}, {"name": "Organizaciones_de_Reino_Unido", "id": 2187110}, {"name": "Clubes_de_Inglaterra", "id": 2499643}, {"name": "Historia_deportiva_de_Reino_Unido", "id": 5374556}], "successors": [{"name": "Equipos_de_fútbol_desaparecidos_de_Inglaterra", "id": 3109553}, {"name": "Selección_de_fútbol_de_Inglaterra", "id": 3140274}, {"name": "Equipos_de_fútbol_de_Londres", "id": 3194042}, {"name": "Equipos_de_fútbol_de_Inglaterra_en_competiciones_internacionales", "id": 5342806}, {"name": "Futbolistas_del_Southport_Football_Club", "id": 6065740}]}