{"name": "Política_de_Francia", "id": 136965, "predecessors": [{"name": "Estados_miembros_de_la_Francofonía", "id": 6402672}, {"name": "Índice_de_categorías", "id": 55702}, {"name": "Política_de_la_Unión_Europea", "id": 194895}], "successors": [{"name": "Quinta_República_Francesa", "id": 336558}, {"name": "Fuerzas_armadas_de_Francia", "id": 227277}, {"name": "Anarquistas_de_Francia", "id": 509105}, {"name": "Comunistas_de_Francia", "id": 535946}, {"name": "Liberales_de_Francia", "id": 1412820}, {"name": "Socialistas_de_Francia", "id": 1510726}, {"name": "Feministas_de_Francia", "id": 1743899}, {"name": "Monárquicos_de_Francia", "id": 4750776}, {"name": "Políticos_de_Unión_por_un_Movimiento_Popular", "id": 3306741}, {"name": "Políticos_de_la_Sección_Francesa_de_la_Internacional_Obrera", "id": 6571122}, {"name": "Miembros_del_Partido_Comunista_Francés", "id": 9634159}, {"name": "Miembros_del_Partido_Republicano_Radical_y_Radical_Socialista", "id": 10310407}, {"name": "Antiguo_Régimen_en_Francia", "id": 704689}, {"name": "Izquierda_abertzale", "id": 1058372}]}