{"name": "Audio_digital", "id": 221028, "predecessors": [{"name": "Audio", "id": 156840}, {"name": "Procesamiento_digital_de_señales", "id": 2932295}, {"name": "Tarjetas_de_sonido", "id": 1311747}, {"name": "Medios_digitales", "id": 5933105}], "successors": [{"name": "Voz_sobre_IP", "id": 393693}, {"name": "Reproductores_de_audio_digital_libres", "id": 467884}, {"name": "Códecs_de_audio", "id": 54626}, {"name": "Software_de_música", "id": 475992}, {"name": "Software_de_audio_libre", "id": 2932243}]}