{"name": "Acontecimientos_musicales", "id": 234952, "predecessors": [{"name": "Eventos_artísticos", "id": 1830571}, {"name": "Música", "id": 50615}], "successors": [{"name": "Festivales_de_música", "id": 234955}, {"name": "Premios_de_música", "id": 309071}, {"name": "Iniciativas_musicales_solidarias", "id": 3145737}, {"name": "Anexos:Giras_musicales", "id": 3364498}, {"name": "Giras_musicales_de_Bob_Dylan", "id": 2243424}, {"name": "Giras_musicales_de_The_Rolling_Stones", "id": 2243563}, {"name": "Giras_musicales_de_The_Who", "id": 6853542}, {"name": "Giras_musicales_de_Bélgica", "id": 10788215}]}