{"name": "Ingeniería_aeroespacial", "id": 2366303, "predecessors": [{"name": "Aviación", "id": 282606}, {"name": "Ingeniería", "id": 65205}], "successors": [{"name": "Mecánica_de_fluidos", "id": 74186}, {"name": "Astrodinámica", "id": 148978}, {"name": "Aerodinámica", "id": 185699}, {"name": "Navegación_aérea", "id": 282984}, {"name": "Ingenieros_aeroespaciales", "id": 4516397}, {"name": "Componentes_de_aeronaves", "id": 4398665}, {"name": "Aeronaves_de_doble_botalón", "id": 7760972}, {"name": "Biplanos", "id": 2516851}, {"name": "Canard", "id": 5333407}, {"name": "Triplanos", "id": 6277015}, {"name": "Aeronaves_de_ala_en_delta_sin_estabilizador_horizontal", "id": 7750954}, {"name": "Transporte_por_avión", "id": 397542}, {"name": "Materiales_compuestos", "id": 74573}, {"name": "Materiales_en_ingeniería", "id": 319318}, {"name": "Minerales_de_níquel", "id": 3222856}, {"name": "Aleaciones_de_níquel", "id": 3655113}, {"name": "Minerales_de_titanio", "id": 3231747}, {"name": "Minerales_de_magnesio", "id": 3221282}, {"name": "Aeronaves_de_ala_alta", "id": 6632414}, {"name": "Aeronaves_de_ala_en_parasol", "id": 7469209}, {"name": "Aeronaves_de_ala_media", "id": 7470636}, {"name": "Aeronaves_de_ala_semialta", "id": 8147999}, {"name": "Aeronaves_de_ala_baja", "id": 8777376}, {"name": "Aviones_tractores_monomotores", "id": 7734632}, {"name": "Aviones_tractores_de_cuatro_motores", "id": 7734706}, {"name": "Aviones_tractores_bimotores", "id": 7736825}, {"name": "Aviones_tractores_trimotores", "id": 7741741}, {"name": "Aviones_propulsores_monomotores", "id": 7734665}, {"name": "Aviones_de_cola_en_T", "id": 7737173}, {"name": "Aeronaves_de_cola_cruciforme", "id": 7750225}, {"name": "Aeronaves_de_cola_doble", "id": 9085203}, {"name": "Helicópteros_monomotores_de_pistón", "id": 7745104}, {"name": "Helicópteros_biturbina", "id": 7759164}, {"name": "Helicópteros_monoturbina", "id": 7872377}]}