{"name": "Archipiélagos_e_islas_del_océano_Pacífico", "id": 2981896, "predecessors": [{"name": "Accidentes_costeros_y_oceánicos", "id": 3412984}, {"name": "Geografía_física", "id": 741956}], "successors": [{"name": "Chiloé", "id": 306937}, {"name": "Islas_Spratly", "id": 4014221}, {"name": "Islas_deshabitadas_del_océano_Pacífico", "id": 5329929}, {"name": "Cultura_de_Filipinas", "id": 115147}, {"name": "Historia_de_Filipinas", "id": 118040}, {"name": "Historia_de_Indonesia", "id": 142387}, {"name": "Cultura_de_Indonesia", "id": 142390}, {"name": "Atolones_de_las_Islas_Marshall", "id": 1012514}, {"name": "Islas_del_archipiélago_de_Chiloé", "id": 1883375}, {"name": "Islas_del_archipiélago_de_las_islas_Galápagos", "id": 2956713}, {"name": "Islas_del_archipiélago_de_Tierra_del_Fuego_de_Chile", "id": 3096871}, {"name": "Archipiélagos_e_islas_de_Nueva_Zelanda", "id": 1883728}, {"name": "Archipiélagos_e_islas_de_Filipinas", "id": 2981976}, {"name": "Archipiélagos_e_islas_de_las_Islas_Salomón", "id": 2982035}, {"name": "Archipiélagos_e_islas_de_Palaos", "id": 2982084}, {"name": "Archipiélagos_e_islas_de_Papúa_Nueva_Guinea", "id": 2982094}, {"name": "Archipiélagos_e_islas_de_Vanuatu", "id": 2982171}, {"name": "Archipiélagos_e_islas_del_océano_Pacífico_de_Perú", "id": 4780787}, {"name": "Archipiélagos_e_islas_del_océano_Pacífico_de_México", "id": 5099508}, {"name": "Archipiélagos_e_islas_del_mar_de_China_Meridional_de_China", "id": 5213702}, {"name": "Atolones_de_Tuamotu", "id": 7434774}, {"name": "Fauna_de_Filipinas", "id": 724829}, {"name": "Flora_de_Filipinas", "id": 1375850}, {"name": "Parques_nacionales_de_Filipinas", "id": 5284071}, {"name": "Fallecidos_en_Manila", "id": 9695165}, {"name": "Archipiélagos_e_islas_de_las_islas_menores_de_la_Sonda", "id": 4870068}]}