{"name": "Equipos_de_fútbol_fundados_en_1911", "id": 3175362, "predecessors": [{"name": "Organizaciones_fundadas_en_1911", "id": 4362393}, {"name": "Índice_de_categorías", "id": 55702}, {"name": "Usos_y_costumbres", "id": 66590}], "successors": [{"name": "Futbolistas_del_PFC_CSKA_Moscú", "id": 4038971}, {"name": "Futbolistas_del_Zamalek_Sporting_Club", "id": 5043712}, {"name": "Entrenadores_del_Zamalek_Sporting_Club", "id": 5043726}, {"name": "Futbolistas_del_Hrvatski_Nogometni_Klub_Hajduk_Split", "id": 2316519}, {"name": "Futbolistas_del_Stade_de_Reims", "id": 5985037}, {"name": "Futbolistas_del_Austria_Viena", "id": 2315966}, {"name": "Futbolistas_del_Molde_FK", "id": 4860469}, {"name": "Futbolistas_del_Anorthosis_Famagusta", "id": 6305618}, {"name": "Futbolistas_del_Polonia_Varsovia", "id": 6081737}, {"name": "Futbolistas_del_Brescia_Calcio", "id": 5147579}, {"name": "Entrenadores_del_Brescia_Calcio", "id": 6103178}, {"name": "Futbolistas_del_Mantova_1911", "id": 10670645}, {"name": "Futbolistas_del_Club_River_Plate", "id": 3152080}]}