{"name": "UEFA", "id": 321411, "predecessors": [{"name": "Organizaciones_deportivas_europeas", "id": 1506961}, {"name": "FIFA", "id": 451535}, {"name": "Comportamiento_humano", "id": 744693}, {"name": "Usos_y_costumbres", "id": 66590}], "successors": [{"name": "Asociaciones_y_federaciones_miembros_de_la_UEFA", "id": 5296042}, {"name": "Selecciones_de_fútbol_sala_de_Europa", "id": 7303785}, {"name": "Selección_de_fútbol_de_Inglaterra", "id": 3140274}, {"name": "Selecciones_de_fútbol_sub-20_de_la_UEFA", "id": 6037072}, {"name": "Estadios_de_la_final_de_la_Liga_de_Campeones_de_la_UEFA", "id": 368811}, {"name": "Estadios_de_la_antigua_categoría_elite_de_la_UEFA", "id": 8996089}, {"name": "Estadios_de_categoría_4_de_la_UEFA", "id": 9000371}, {"name": "Futbolistas_de_la_selección_femenina_de_fútbol_de_España", "id": 9492544}, {"name": "Futbolistas_de_la_selección_femenina_de_fútbol_de_Francia", "id": 9492518}]}