{"name": "Música_en_el_siglo_XXI", "id": 4222329, "predecessors": [{"name": "Arte_contemporáneo", "id": 9792877}, {"name": "Arte", "id": 51311}, {"name": "Cronología", "id": 407929}], "successors": [{"name": "Músicos_del_siglo_XXI", "id": 4897411}, {"name": "Canciones_de_2000", "id": 739236}, {"name": "Canciones_de_2003", "id": 838922}, {"name": "Canciones_de_2004", "id": 927555}, {"name": "Canciones_de_2005", "id": 1021594}, {"name": "Canciones_de_2007", "id": 1218917}, {"name": "Canciones_de_2006", "id": 1267179}, {"name": "Canciones_de_2002", "id": 1336537}, {"name": "Canciones_de_2001", "id": 1337367}, {"name": "Canciones_de_2008", "id": 1596537}, {"name": "Canciones_de_2009", "id": 2040474}, {"name": "Grupos_de_música_formados_en_los_años_2000", "id": 4637231}, {"name": "Grupos_de_música_formados_en_los_años_2010", "id": 5184115}, {"name": "Grupos_de_música_de_los_años_2010", "id": 4830810}, {"name": "Grupos_de_música_de_los_años_2000", "id": 4831100}, {"name": "Grupos_de_música_de_los_años_2020", "id": 9236398}, {"name": "Álbumes_recopilatorios_de_2004", "id": 4605414}, {"name": "Álbumes_recopilatorios_de_2002", "id": 4611800}, {"name": "Álbumes_recopilatorios_de_2006", "id": 4631464}, {"name": "Álbumes_recopilatorios_de_2008", "id": 4789710}, {"name": "Álbumes_recopilatorios_de_2007", "id": 4789713}, {"name": "Álbumes_recopilatorios_de_2009", "id": 4789729}, {"name": "Álbumes_recopilatorios_de_2005", "id": 4789731}, {"name": "Álbumes_recopilatorios_de_2000", "id": 4789761}, {"name": "Álbumes_recopilatorios_de_2003", "id": 4789796}, {"name": "Álbumes_recopilatorios_de_2001", "id": 4789807}, {"name": "Álbumes_recopilatorios_de_2010", "id": 4792486}, {"name": "Álbumes_recopilatorios_de_2011", "id": 4836148}, {"name": "Álbumes_recopilatorios_de_2012", "id": 5073593}, {"name": "Compositores_de_música_clásica_del_siglo_XXI", "id": 3685226}, {"name": "España_en_Eurovisión", "id": 4090655}, {"name": "Músicos_de_España_del_siglo_XXI", "id": 4921465}, {"name": "Pianistas_de_España_del_siglo_XXI", "id": 10372865}, {"name": "Músicos_de_Japón_del_siglo_XXI", "id": 6316840}, {"name": "Grupos_de_música_separados_en_2012", "id": 6515150}, {"name": "Grupos_de_música_separados_en_2018", "id": 8370164}, {"name": "Grupos_de_rap_de_España", "id": 617990}, {"name": "Disc_jockeys_de_España", "id": 3195686}, {"name": "Álbumes_de_2020", "id": 9111531}, {"name": "Álbumes_de_2021", "id": 9702273}, {"name": "Álbumes_de_2022", "id": 10049718}, {"name": "Álbumes_de_2023", "id": 10346703}, {"name": "Canciones_de_2020", "id": 9248867}, {"name": "Canciones_de_2021", "id": 9749962}, {"name": "Canciones_de_2022", "id": 10123974}, {"name": "Canciones_de_2023", "id": 10435860}, {"name": "Sencillos_de_2020", "id": 9239728}, {"name": "Sencillos_de_2021", "id": 9749964}, {"name": "Sencillos_de_2022", "id": 10123975}, {"name": "Sencillos_de_2023", "id": 10435858}, {"name": "Álbumes_pospuestos_debido_a_la_pandemia_de_COVID-19", "id": 9400544}, {"name": "Cantantes_femeninas_de_Corea_del_Sur_del_siglo_XXI", "id": 10597983}, {"name": "Cantantes_femeninas_de_Japón_del_siglo_XXI", "id": 10597999}, {"name": "Cantantes_femeninas_de_Estados_Unidos_del_siglo_XXI", "id": 10602933}]}