{"name": "Arquitectura_de_España_del_siglo_XVII", "id": 4938630, "predecessors": [{"name": "Arquitectura_del_siglo_XVII", "id": 1744942}, {"name": "España_en_el_siglo_XVII", "id": 2493122}, {"name": "Arquitectura_de_España", "id": 92382}, {"name": "Edad_Moderna", "id": 245731}], "successors": [{"name": "Arquitectos_de_España_del_siglo_XVII", "id": 1385845}, {"name": "Castillos_de_España_del_siglo_XVII", "id": 6503025}, {"name": "Palacios_de_España_del_siglo_XVII", "id": 6512358}, {"name": "Conventos_de_España_del_siglo_XVII", "id": 6513465}, {"name": "Puentes_de_España_del_siglo_XVII", "id": 6603961}, {"name": "Esculturas_urbanas_de_España_del_siglo_XVII", "id": 7413334}]}