{"name": "Equipos_de_fútbol_fundados_en_2012", "id": 5059722, "predecessors": [{"name": "Fútbol_en_2012", "id": 1893138}, {"name": "Organizaciones_fundadas_en_2012", "id": 5122869}, {"name": "Cronología", "id": 407929}, {"name": "Usos_y_costumbres", "id": 66590}], "successors": [{"name": "Futbolistas_del_Club_Llaneros", "id": 5337867}, {"name": "Futbolistas_del_Jaguares_de_Córdoba", "id": 6042158}, {"name": "Futbolistas_del_Club_de_Fútbol_Lorca_Deportiva", "id": 6885694}, {"name": "Entrenadores_del_Club_Deportivo_Badajoz", "id": 2660463}, {"name": "Futbolistas_del_Club_Deportivo_Badajoz", "id": 2730662}, {"name": "Futbolistas_del_Fútbol_Club_Carlos_Stein", "id": 10169487}, {"name": "Futbolistas_del_Club_Polideportivo_El_Ejido", "id": 7482920}]}