{"name": "Parque_nacional_Los_Glaciares", "id": 5210926, "predecessors": [{"name": "Parques_nacionales_de_Argentina", "id": 5004888}, {"name": "Patrimonio_de_la_Humanidad_en_Argentina", "id": 3478293}, {"name": "Turismo_en_la_provincia_de_Santa_Cruz_(Argentina)", "id": 1810991}, {"name": "Áreas_naturales_protegidas_de_la_provincia_de_Santa_Cruz_(Argentina)", "id": 6217780}, {"name": "Reservas_naturales_de_Argentina", "id": 416088}, {"name": "Rutas_nacionales_de_Argentina", "id": 621424}, {"name": "Historia_de_América", "id": 51466}, {"name": "Índice_de_categorías", "id": 55702}], "successors": []}