{"name": "Política_de_México", "id": 53394, "predecessors": [{"name": "Iberoamérica", "id": 51490}, {"name": "Índice_de_categorías", "id": 55702}], "successors": [{"name": "Partidos_políticos_de_México", "id": 157419}, {"name": "Derecho_de_México", "id": 267162}, {"name": "Primeras_damas_de_México", "id": 3107155}, {"name": "Derechos_humanos_en_México", "id": 3174150}, {"name": "Escándalos_políticos_en_México", "id": 3227542}, {"name": "Organizaciones_políticas_de_México", "id": 5146083}, {"name": "Municipios_de_México_regidos_por_el_sistema_de_Usos_y_Costumbres", "id": 7210228}, {"name": "Municipios_de_México", "id": 452600}, {"name": "Política_de_Baja_California", "id": 1657507}, {"name": "Diplomáticos_de_México", "id": 620807}, {"name": "Misiones_diplomáticas_de_México", "id": 1027012}, {"name": "Relaciones_bilaterales_de_México", "id": 2937419}, {"name": "EZLN", "id": 746937}, {"name": "Comunistas_de_México", "id": 672641}, {"name": "Conservadores_de_México", "id": 869029}, {"name": "Liberales_de_México", "id": 869071}, {"name": "Feministas_de_México", "id": 3090008}, {"name": "Miembros_del_Partido_Movimiento_Ciudadano", "id": 6527888}]}