{"name": "Liberalismo", "id": 54856, "predecessors": [{"name": "Capitalismo", "id": 2985675}, {"name": "Ideología", "id": 119264}], "successors": [{"name": "Estado_de_bienestar", "id": 711698}, {"name": "Literatura_liberal", "id": 776681}, {"name": "Historia_del_liberalismo", "id": 1151627}, {"name": "Conceptos_liberales", "id": 1355611}, {"name": "Libertarismo", "id": 3827613}, {"name": "Partidos_liberales", "id": 174106}, {"name": "Institutos_libertarios", "id": 1150675}, {"name": "Repúblicas", "id": 10011796}, {"name": "Secretarios_generales_de_partidos_comunistas", "id": 2155412}, {"name": "Republicanos_de_Australia", "id": 5925678}, {"name": "Republicanos_de_España", "id": 7057197}, {"name": "Republicanos_de_Reino_Unido", "id": 7062394}, {"name": "Socialistas_de_Francia", "id": 1510726}, {"name": "Partidos_radicales", "id": 1064260}, {"name": "Radicales_de_Argentina", "id": 274051}, {"name": "Políticos_del_Partido_Liberal_Colombiano", "id": 883711}, {"name": "Políticos_de_Izquierda_Republicana", "id": 1385226}, {"name": "Radicales_de_Chile", "id": 1704669}, {"name": "Políticos_del_Partido_Republicano_Radical", "id": 4203210}, {"name": "Miembros_del_Partido_Republicano_Radical_y_Radical_Socialista", "id": 10310407}]}