{"name": "Fósiles", "id": 554861, "predecessors": [{"name": "Especies_extintas", "id": 183983}, {"name": "Paleontología", "id": 52105}], "successors": [{"name": "Fósiles_vivientes", "id": 648379}, {"name": "Peces_prehistóricos", "id": 1262392}, {"name": "Fósiles_vegetales", "id": 2147448}, {"name": "Icnofósiles", "id": 3478292}, {"name": "Fósiles_del_Cretáceo", "id": 1214081}, {"name": "Fósiles_del_Jurásico", "id": 1242985}, {"name": "Fósiles_del_Triásico", "id": 1274194}, {"name": "Dinosaurios_del_Cretácico", "id": 402485}, {"name": "Dinosaurios_de_ficción", "id": 2990217}, {"name": "Anatomía_de_las_aves", "id": 2353884}, {"name": "Dinosaurios_del_Triásico_Superior", "id": 9985114}, {"name": "Dinosaurios_del_Jurásico_Superior", "id": 9979793}, {"name": "Dinosaurios_del_Jurásico_Inferior", "id": 9979808}, {"name": "Dinosaurios_del_Jurásico_Medio", "id": 9979814}, {"name": "Familias_de_aves", "id": 2366172}, {"name": "Enantiornithes", "id": 2474568}, {"name": "Géneros_de_aves", "id": 2742998}, {"name": "Subfamilias_de_aves", "id": 5501578}, {"name": "Tribus_de_aves", "id": 6090803}, {"name": "Órdenes_de_aves", "id": 6433022}, {"name": "Familias_monotípicas_de_aves", "id": 8636362}, {"name": "Passeriformes", "id": 196532}, {"name": "Trochilidae", "id": 477976}, {"name": "Phasianidae", "id": 456451}, {"name": "Falco", "id": 2184181}, {"name": "Anas", "id": 890384}, {"name": "Ducula", "id": 1318821}, {"name": "Ptilinopus", "id": 1817851}, {"name": "Columba", "id": 2781417}, {"name": "Centropus", "id": 4522241}, {"name": "Caprimulgus", "id": 2500493}, {"name": "Pterodroma", "id": 1871537}, {"name": "Picumnus", "id": 4602444}, {"name": "Charadrius", "id": 936000}, {"name": "Larus", "id": 2463063}, {"name": "Fósiles_de_Oceanía", "id": 1214084}, {"name": "Fósiles_de_América", "id": 1214088}, {"name": "Fósiles_de_Asia", "id": 1242986}, {"name": "Fósiles_de_Europa", "id": 1243013}, {"name": "Fósiles_de_África", "id": 4875843}, {"name": "Aerodramus", "id": 5559495}, {"name": "Fósiles_del_Pérmico", "id": 1667135}, {"name": "Fósiles_del_Carbonífero", "id": 1667144}, {"name": "Fósiles_del_Mioceno", "id": 1214086}, {"name": "Fósiles_del_Pleistoceno", "id": 1214093}, {"name": "Fósiles_del_Eoceno", "id": 1214195}, {"name": "Psilopogon", "id": 7023246}, {"name": "Cacatúas_y_papagayos_(Psittaciformes)_no_amenazados", "id": 4265155}, {"name": "Cacatúas_y_papagayos_(Psittaciformes)_en_estado_vulnerable", "id": 4265201}, {"name": "Cacatúas_y_papagayos_(Psittaciformes)_en_peligro_de_extinción", "id": 4265204}, {"name": "Cacatúas_y_papagayos_(Psittaciformes)_medianamente_amenazados", "id": 4265208}, {"name": "Charadriiformes_medianamente_amenazadas", "id": 4265330}, {"name": "Charadriiformes_no_amenazadas", "id": 4265336}, {"name": "Gallináceas_(Galliformes)_en_estado_vulnerable", "id": 4265312}, {"name": "Gallináceas_(Galliformes)_medianamente_amenazadas", "id": 4265331}, {"name": "Gallináceas_(Galliformes)_no_amenazadas", "id": 4265337}, {"name": "Patos_y_gansos_(Anseriformes)_no_amenazados", "id": 4265335}, {"name": "Rapaces_diurnas_(Falconiformes)_no_amenazadas", "id": 4265339}, {"name": "Amazona_(género)", "id": 1814360}, {"name": "Dinosaurios_de_Australia", "id": 5073673}, {"name": "Aves_de_Australia", "id": 903142}, {"name": "Aves_de_India", "id": 1126516}, {"name": "Aves_de_México", "id": 1157053}, {"name": "Aves_de_Argentina", "id": 1274824}, {"name": "Aves_de_Cuba", "id": 1274961}, {"name": "Aves_de_Bolivia", "id": 1275454}, {"name": "Aves_de_Chile", "id": 1275457}, {"name": "Aves_de_Perú", "id": 1275460}, {"name": "Aves_de_Filipinas", "id": 1277850}, {"name": "Aves_de_Venezuela", "id": 1278324}, {"name": "Aves_de_Colombia", "id": 1278325}, {"name": "Aves_de_Brasil", "id": 1278329}, {"name": "Aves_de_Ecuador", "id": 1278332}, {"name": "Aves_de_Uruguay", "id": 1278977}, {"name": "Aves_de_Jamaica", "id": 1377104}, {"name": "Listas_de_aves_por_país", "id": 2195839}, {"name": "Treron", "id": 4491615}, {"name": "Ornitología", "id": 173371}, {"name": "Aves_nacionales", "id": 1211292}, {"name": "Nombres_vernáculos_de_aves", "id": 2383968}, {"name": "Palomas_domésticas", "id": 2601167}, {"name": "Aviarios", "id": 6836073}, {"name": "Patos", "id": 10945359}, {"name": "Sitios_relevantes_para_la_observación_de_aves_en_Argentina", "id": 4826712}, {"name": "Sitios_relevantes_para_la_observación_de_aves_en_Perú", "id": 4828993}, {"name": "Sitios_relevantes_para_la_observación_de_aves_en_Venezuela", "id": 6229736}, {"name": "Aves_legendarias", "id": 440600}, {"name": "Aves_de_ficción", "id": 2589905}, {"name": "Escudos_con_aves", "id": 9024500}, {"name": "Aves_en_el_arte", "id": 9024501}, {"name": "Platos_de_pollo", "id": 1885674}, {"name": "Aves_migratorias", "id": 904107}, {"name": "Aves_marinas", "id": 4548324}, {"name": "Aves_no_voladoras", "id": 6933277}, {"name": "Águilas", "id": 9036435}, {"name": "Aves_descritas_en_1758", "id": 10484438}, {"name": "Aves_descritas_en_1824", "id": 10937320}, {"name": "Aves_descritas_en_1905", "id": 10938107}, {"name": "Aves_descritas_en_1865", "id": 10938837}, {"name": "Aves_descritas_en_1907", "id": 10958856}, {"name": "Fósiles_de_Argentina", "id": 4671029}]}