{"name": "Estados_y_territorios_desaparecidos_en_1886", "id": 5651524, "predecessors": [{"name": "Años", "id": 407751}, {"name": "Geografía_política", "id": 1708360}, {"name": "Cronología", "id": 407929}], "successors": [{"name": "Estado_Soberano_de_Panamá", "id": 7671270}, {"name": "Estado_Soberano_de_Antioquia", "id": 7671384}, {"name": "Estado_Soberano_de_Boyacá", "id": 7690264}, {"name": "Estado_Soberano_de_Cundinamarca", "id": 7694130}, {"name": "Estado_Soberano_del_Magdalena", "id": 7711305}, {"name": "Estado_Soberano_de_Bolívar", "id": 7713964}, {"name": "Estado_Soberano_de_Santander", "id": 7718330}]}