{"name": "Star_Wars", "id": 61470, "predecessors": [{"name": "Space_opera", "id": 10174339}, {"name": "Lugares_ficticios", "id": 1132371}, {"name": "Cine", "id": 50592}, {"name": "Ciencias_sociales", "id": 54517}, {"name": "Franquicias_de_medios", "id": 6537682}, {"name": "Organizaciones_ficticias", "id": 343338}, {"name": "Franquicias_de_Disney", "id": 9247269}, {"name": "Cultura", "id": 51310}], "successors": [{"name": "Vehículos_de_Star_Wars", "id": 77617}, {"name": "Personajes_de_Star_Wars", "id": 87792}, {"name": "Videojuegos_de_Star_Wars", "id": 298164}, {"name": "Libros_de_Star_Wars", "id": 333138}, {"name": "Reparto_de_Star_Wars", "id": 3171335}]}