{"name": "Armas", "id": 650148, "predecessors": [{"name": "Guerra", "id": 69474}, {"name": "Armamento", "id": 68567}], "successors": [{"name": "Armas_de_fuego", "id": 125471}, {"name": "Artillería", "id": 125472}, {"name": "Armas_de_asedio", "id": 264741}, {"name": "Armas_de_las_artes_marciales_de_Japón", "id": 341531}, {"name": "Tratados_para_el_control_de_armamento", "id": 551602}, {"name": "Armas_antiaéreas", "id": 1739015}, {"name": "Armas_ficticias", "id": 1873670}, {"name": "Armas_espaciales", "id": 3489838}, {"name": "Misiles_antiaéreos", "id": 1320488}, {"name": "Artillería_de_cohetes", "id": 1690740}, {"name": "Misiles_de_crucero", "id": 3277271}, {"name": "Misiles_aire-superficie", "id": 3277531}, {"name": "Misiles_antibuque", "id": 3577781}, {"name": "Diseñadores_de_armas_de_fuego", "id": 841136}, {"name": "Artillería_naval", "id": 2129623}, {"name": "Torpedos", "id": 1853435}, {"name": "Granadas", "id": 1781801}, {"name": "Bombas", "id": 1853420}, {"name": "Armas_nucleares", "id": 274691}, {"name": "Armas_arrojadizas", "id": 130437}, {"name": "Misiles_balísticos", "id": 7592184}, {"name": "Escudos_con_flechas", "id": 9047469}, {"name": "Escudos_con_lanzas", "id": 9048351}, {"name": "Escudos_con_espadas", "id": 9049858}]}