{"name": "Literatura_medieval", "id": 66947, "predecessors": [{"name": "Historia_de_la_literatura", "id": 1079721}, {"name": "Cultura", "id": 51310}, {"name": "Historia_de_la_cultura", "id": 791575}, {"name": "Arte", "id": 51311}], "successors": [{"name": "Historiadores_medievales", "id": 278123}, {"name": "Literatura_medieval_escandinava", "id": 302685}, {"name": "Literatura_bizantina", "id": 2744981}, {"name": "Libros_de_horas", "id": 4619178}, {"name": "Mitología_germana_en_la_literatura_medieval", "id": 5321314}, {"name": "Libros_de_caballerías", "id": 158005}, {"name": "Códices", "id": 913887}, {"name": "Crónicas_medievales", "id": 1429520}, {"name": "Fuentes_musicales_de_la_Edad_Media", "id": 3268231}, {"name": "Obras_literarias_medievales_de_España", "id": 3306337}, {"name": "Literatura_medieval_de_España", "id": 107639}, {"name": "Literatura_medieval_de_Alemania", "id": 3473635}]}