{"name": "Revistas_científicas", "id": 73526, "predecessors": [{"name": "Publicaciones_científicas", "id": 3671238}, {"name": "Revistas", "id": 55832}], "successors": [{"name": "Revistas_científicas_de_acceso_abierto", "id": 5061163}, {"name": "Revistas_científicas_de_España", "id": 1800797}, {"name": "Revistas_científicas_de_Estados_Unidos", "id": 5061112}, {"name": "Revistas_científicas_de_Alemania", "id": 5076623}, {"name": "Revistas_científicas_de_Argentina", "id": 5301713}, {"name": "Revistas_científicas_de_México", "id": 5421445}, {"name": "Revistas_científicas_de_Francia", "id": 5423735}, {"name": "Revistas_científicas_de_los_Países_Bajos", "id": 5426405}, {"name": "Revistas_publicadas_por_Oxford_University_Press", "id": 5061080}, {"name": "Revistas_científicas_en_inglés", "id": 5061058}, {"name": "Revistas_científicas_en_francés", "id": 5061137}, {"name": "Revistas_científicas_en_alemán", "id": 5062739}, {"name": "Revistas_científicas_en_español", "id": 5062748}, {"name": "Revistas_científicas_multilingües", "id": 5063668}, {"name": "Revistas_científicas_en_portugués", "id": 5421426}]}