{"name": "Funcionarios_de_México", "id": 7524736, "predecessors": [{"name": "Política_de_México", "id": 53394}, {"name": "Mexicanos", "id": 168599}, {"name": "Sociedad", "id": 61818}], "successors": [{"name": "Diplomáticos_de_México", "id": 620807}, {"name": "Gobernantes_de_México", "id": 73908}, {"name": "Conservadores_de_México", "id": 869029}, {"name": "Liberales_de_México", "id": 869071}, {"name": "Senadores_de_México", "id": 1807624}, {"name": "Socialistas_de_México", "id": 2305647}, {"name": "Políticos_LGBT_de_México", "id": 5421623}, {"name": "Políticas_de_México", "id": 5776901}, {"name": "Políticos_asesinados_de_México", "id": 8427710}, {"name": "Ministros_de_la_Suprema_Corte_de_Justicia_de_la_Nación", "id": 617580}, {"name": "Políticos_de_Oaxaca", "id": 520907}, {"name": "Políticos_de_Guanajuato", "id": 566059}, {"name": "Políticos_de_Nayarit", "id": 758745}, {"name": "Políticos_de_Veracruz", "id": 762288}, {"name": "Políticos_de_Puebla", "id": 1032952}, {"name": "Políticos_de_Coahuila", "id": 1279406}, {"name": "Políticos_de_Ciudad_de_México", "id": 1577291}, {"name": "Políticos_de_Tabasco", "id": 1701433}, {"name": "Políticos_de_Nuevo_León", "id": 1800309}, {"name": "Políticos_de_Quintana_Roo", "id": 1816612}, {"name": "Políticos_de_Jalisco", "id": 2034134}, {"name": "Políticos_de_Sonora", "id": 2245696}, {"name": "Políticos_de_Guerrero", "id": 2749853}, {"name": "Políticos_de_Querétaro", "id": 2990955}, {"name": "Políticos_de_Michoacán", "id": 3437910}, {"name": "Políticos_de_Yucatán", "id": 3744056}, {"name": "Políticos_de_Chiapas", "id": 4154183}, {"name": "Políticos_de_Sinaloa", "id": 4399422}, {"name": "Políticos_de_Aguascalientes", "id": 4518860}, {"name": "Políticos_de_Baja_California", "id": 4520894}, {"name": "Políticos_de_Campeche", "id": 4521159}, {"name": "Políticos_de_Chihuahua", "id": 4534054}, {"name": "Políticos_de_Tamaulipas", "id": 4610336}, {"name": "Políticos_de_Hidalgo", "id": 5305493}, {"name": "Políticos_de_Zacatecas", "id": 5415572}, {"name": "Políticos_de_Durango", "id": 5549169}, {"name": "Políticos_de_San_Luis_Potosí", "id": 5556230}, {"name": "Políticos_del_Estado_de_México", "id": 5556278}, {"name": "Políticos_de_Baja_California_Sur", "id": 5710144}, {"name": "Políticos_de_Tlaxcala", "id": 6941037}, {"name": "Políticos_de_Colima", "id": 7047661}, {"name": "Políticos_de_Morelos", "id": 7078869}, {"name": "Presidentes_del_Partido_de_la_Revolución_Democrática", "id": 652389}, {"name": "Presidentes_del_Partido_Revolucionario_Institucional", "id": 7078896}, {"name": "Presidentes_del_Partido_Acción_Nacional", "id": 7080561}, {"name": "Funcionarios_de_la_Ciudad_de_México", "id": 10271734}, {"name": "Magistrados_de_los_Tribunales_Superiores_de_Justicia_de_México", "id": 10271846}, {"name": "Miembros_del_PRI_de_Tlaxcala", "id": 7055511}, {"name": "Miembros_del_PRI_de_Michoacán", "id": 7055515}, {"name": "Miembros_del_PRI_de_Colima", "id": 7055520}, {"name": "Miembros_del_PRI_de_Guerrero", "id": 7055522}, {"name": "Miembros_del_PRI_de_Quintana_Roo", "id": 7055526}, {"name": "Miembros_del_PRI_de_Aguascalientes", "id": 7055536}, {"name": "Miembros_del_PRI_del_Estado_de_México", "id": 7055538}, {"name": "Miembros_del_PRI_de_Chihuahua", "id": 7055540}, {"name": "Miembros_del_PRI_de_Sinaloa", "id": 7055546}, {"name": "Miembros_del_PRI_de_Guanajuato", "id": 7055555}, {"name": "Miembros_del_PRI_de_Puebla", "id": 7055560}, {"name": "Miembros_del_PRI_de_Tamaulipas", "id": 7055561}, {"name": "Miembros_del_PRI_de_Yucatán", "id": 7055569}, {"name": "Miembros_del_PRI_de_Oaxaca", "id": 7055583}, {"name": "Miembros_del_PRI_de_Sonora", "id": 7055594}, {"name": "Miembros_del_PRI_de_la_Ciudad_de_México", "id": 7055603}, {"name": "Miembros_del_PRI_de_Hidalgo", "id": 7055605}, {"name": "Miembros_del_PRI_de_Durango", "id": 7055611}, {"name": "Miembros_del_PRI_de_Baja_California", "id": 7055669}, {"name": "Miembros_del_PRI_de_Tabasco", "id": 7055670}, {"name": "Miembros_del_PRI_de_Chiapas", "id": 7055680}, {"name": "Miembros_del_PRI_de_Jalisco", "id": 7055745}, {"name": "Miembros_del_PRI_de_Querétaro", "id": 7055758}, {"name": "Miembros_del_PRI_de_Zacatecas", "id": 7055760}, {"name": "Miembros_del_PRI_de_San_Luis_Potosí", "id": 7056003}, {"name": "Miembros_del_PRI_de_Veracruz", "id": 7061779}, {"name": "Miembros_del_PRI_de_Nayarit", "id": 7061786}, {"name": "Miembros_del_PRI_de_Baja_California_Sur", "id": 7061791}, {"name": "Miembros_del_PRI_de_Coahuila", "id": 7061809}, {"name": "Miembros_del_PRI_de_Morelos", "id": 7078260}, {"name": "Miembros_del_PRI_de_Campeche", "id": 7078887}, {"name": "Miembros_del_PAN_de_Sonora", "id": 8426731}, {"name": "Miembros_del_PAN_de_Jalisco", "id": 8426742}, {"name": "Miembros_del_PAN_de_Baja_California", "id": 8427698}, {"name": "Miembros_del_PAN_de_Veracruz", "id": 8428511}, {"name": "Miembros_del_PAN_de_Chihuahua", "id": 8436399}, {"name": "Miembros_del_PAN_de_Tamaulipas", "id": 8436402}, {"name": "Miembros_del_PAN_de_la_Ciudad_de_México", "id": 8436406}, {"name": "Miembros_del_PAN_de_Yucatán", "id": 8436408}, {"name": "Miembros_del_PAN_de_Guanajuato", "id": 8436963}, {"name": "Miembros_del_PAN_de_Michoacán", "id": 8437185}]}