{"name": "Futurología", "id": 768524, "predecessors": [{"name": "Innovación", "id": 1831217}, {"name": "Ciencia", "id": 1733769}, {"name": "Conocimiento", "id": 703218}, {"name": "Tiempo", "id": 211414}], "successors": [{"name": "Inteligencia_artificial", "id": 88769}, {"name": "Transhumanismo", "id": 379742}, {"name": "Colonización_del_espacio", "id": 1149332}, {"name": "Futurólogos", "id": 1837229}, {"name": "Tecnologías_emergentes", "id": 5549984}, {"name": "Complejidad_computacional", "id": 241298}, {"name": "Teoría_del_caos", "id": 690040}, {"name": "Procesamiento_digital_de_señales", "id": 2932295}, {"name": "Neurociencia_computacional", "id": 3365684}, {"name": "Humanidades_digitales", "id": 6109631}, {"name": "Biología_computacional", "id": 10248545}]}