{"name": "Mujeres", "id": 7700167, "predecessors": [{"name": "Mujer", "id": 82033}, {"name": "Personalidad", "id": 4496858}], "successors": [{"name": "Mujeres_ficticias", "id": 7107430}, {"name": "Canciones_sobre_mujeres", "id": 9167449}, {"name": "Mexicanas", "id": 5510769}, {"name": "Mujeres_de_Estados_Unidos", "id": 7303440}, {"name": "Colombianas", "id": 5167406}, {"name": "Mujeres_de_Argentina", "id": 5514904}, {"name": "Ecuatorianas", "id": 6269928}, {"name": "Bolivianas", "id": 6397341}, {"name": "Lesbianas_de_Brasil", "id": 10423395}, {"name": "Mujeres_trans_de_Brasil", "id": 10702091}, {"name": "Uruguayas_del_siglo_XX", "id": 8784889}, {"name": "Uruguayas_del_siglo_XXI", "id": 8784894}, {"name": "Guatemaltecas", "id": 5989978}, {"name": "Mujeres_de_Nicaragua", "id": 7391043}, {"name": "Dominicanas", "id": 6862090}, {"name": "Mujeres_nazis", "id": 5010654}, {"name": "Lesbianas_de_Alemania", "id": 10461927}, {"name": "Mujeres_de_la_Antigua_Grecia", "id": 5035189}, {"name": "Lesbianas_de_España", "id": 10422983}, {"name": "Princesas_británicas", "id": 4992379}, {"name": "Mujeres_de_la_época_victoriana", "id": 5138100}, {"name": "Mujeres_de_la_época_georgiana", "id": 5186697}, {"name": "Grandes_duquesas_de_Rusia", "id": 9384766}, {"name": "Escritoras_de_Portugal", "id": 5685017}, {"name": "Políticas_de_Portugal", "id": 5721640}, {"name": "Deportistas_femeninas_de_Bulgaria", "id": 8726506}, {"name": "Vitorianas", "id": 7102722}, {"name": "Mujeres_de_Palestina", "id": 7667392}, {"name": "Mujeres_galardonadas_con_el_Premio_Israel", "id": 5533499}, {"name": "Azerbaiyanas_del_siglo_XX", "id": 8663894}, {"name": "Azerbaiyanas_del_siglo_XXI", "id": 8663905}, {"name": "Políticas_de_Afganistán", "id": 6635964}, {"name": "Francesas_del_siglo_XX", "id": 8678813}, {"name": "Francesas_del_siglo_XIX", "id": 8679175}, {"name": "Francesas_del_siglo_XXI", "id": 8679182}, {"name": "Francesas_del_siglo_XVII", "id": 8679187}, {"name": "Francesas_del_siglo_XVIII", "id": 8679230}, {"name": "Indonesias_del_siglo_XX", "id": 8700552}, {"name": "Indonesias_del_siglo_XXI", "id": 8700559}, {"name": "Mujeres_de_Israel_del_siglo_XX", "id": 8706075}, {"name": "Mujeres_de_Israel_del_siglo_XXI", "id": 8706078}, {"name": "Italianas_del_siglo_XX", "id": 8707027}, {"name": "Italianas_del_siglo_XXI", "id": 8707052}, {"name": "Italianas_del_siglo_XIX", "id": 8707055}, {"name": "Italianas_del_siglo_XVIII", "id": 8707058}, {"name": "Italianas_del_siglo_XVII", "id": 8707060}, {"name": "Italianas_del_siglo_XVI", "id": 8707061}, {"name": "Italianas_del_siglo_XV", "id": 8707268}, {"name": "Italianas_del_siglo_XIII", "id": 9039733}, {"name": "Libanesas_del_siglo_XX", "id": 8709451}, {"name": "Libanesas_del_siglo_XXI", "id": 8709455}, {"name": "Lituanas_del_siglo_XX", "id": 8710263}, {"name": "Lituanas_del_siglo_XXI", "id": 8710266}, {"name": "Surcoreanas_del_siglo_XXI", "id": 8749242}, {"name": "Surcoreanas_del_siglo_XX", "id": 8749250}, {"name": "Georgianas_del_siglo_XX", "id": 8795432}, {"name": "Georgianas_del_siglo_XXI", "id": 8795435}, {"name": "Portuguesas_del_siglo_XX", "id": 8973598}, {"name": "Portuguesas_del_siglo_XXI", "id": 8973661}, {"name": "Jordanas_del_siglo_XXI", "id": 8855684}, {"name": "Neerlandesas_del_siglo_XXI", "id": 8886589}, {"name": "Neerlandesas_del_siglo_XX", "id": 8886594}, {"name": "Neerlandesas_del_siglo_XVII", "id": 8967739}, {"name": "Cantantes_femeninas_de_Malasia", "id": 7942546}, {"name": "Rusas_del_siglo_XIX", "id": 8498606}, {"name": "Rusas_del_siglo_XX", "id": 8499913}, {"name": "Rusas_del_siglo_XXI", "id": 8784971}, {"name": "Polacas_del_siglo_XX", "id": 8970714}, {"name": "Polacas_del_siglo_XXI", "id": 8970742}, {"name": "Mujeres_de_Pakistán_del_siglo_XXI", "id": 8976466}, {"name": "Tailandesas_del_siglo_XXI", "id": 8984018}, {"name": "Taiwanesas_del_siglo_XXI", "id": 8984523}, {"name": "Actrices_de_Taiwán", "id": 7781985}, {"name": "Cantantes_femeninas_de_Taiwán", "id": 7782400}, {"name": "Rumanas_del_siglo_XX", "id": 8985714}, {"name": "Rumanas_del_siglo_XXI", "id": 8985871}, {"name": "Serbias_del_siglo_XX", "id": 8992288}, {"name": "Serbias_del_siglo_XXI", "id": 8992291}, {"name": "Ucranianas_del_siglo_XX", "id": 9000720}, {"name": "Ucranianas_del_siglo_XXI", "id": 9000729}, {"name": "Suizas_del_siglo_XXI", "id": 9000935}, {"name": "Suizas_del_siglo_XX", "id": 9000938}, {"name": "Turcas_del_siglo_XX", "id": 9013424}, {"name": "Turcas_del_siglo_XXI", "id": 9013425}, {"name": "Uzbekas_del_siglo_XXI", "id": 9019987}, {"name": "Mujeres_en_la_guerra_civil_española", "id": 9511082}, {"name": "Deportistas_femeninas_de_España", "id": 7513024}, {"name": "Organizaciones_feministas_de_España", "id": 7358820}, {"name": "Futbolistas_del_Athletic_Club_(femenino)", "id": 4478559}, {"name": "Futbolistas_del_Levante_Unión_Deportiva_Femenino", "id": 4974458}, {"name": "Futbolistas_del_Fútbol_Club_Barcelona_Femenino", "id": 5220641}, {"name": "Futbolistas_del_Rayo_Vallecano_Femenino", "id": 5220697}, {"name": "Futbolistas_del_Real_Club_Deportivo_Espanyol_Femenino", "id": 5221219}, {"name": "Futbolistas_del_Club_Atlético_de_Madrid_Femenino", "id": 6276529}, {"name": "Futbolistas_de_la_Real_Sociedad_de_Fútbol_(femenino)", "id": 6296635}, {"name": "Futbolistas_del_Zaragoza_Club_de_Fútbol_Femenino", "id": 7634592}, {"name": "Futbolistas_de_la_Unión_Deportiva_Granadilla_Tenerife_Sur", "id": 7657879}, {"name": "Futbolistas_del_Sporting_Club_de_Huelva", "id": 7757218}, {"name": "Futbolistas_del_Sevilla_Fútbol_Club_(femenino)", "id": 7797336}, {"name": "Futbolistas_del_Valencia_Club_de_Fútbol_Femenino", "id": 7800524}, {"name": "Futbolistas_del_Madrid_Club_de_Fútbol_Femenino", "id": 8390002}, {"name": "Futbolistas_del_Real_Madrid_Club_de_Fútbol_Femenino", "id": 9592463}, {"name": "Nobles_italianas_del_siglo_XIV", "id": 10172106}, {"name": "Nobles_italianas_del_siglo_XV", "id": 10172107}, {"name": "Nobles_italianas_del_siglo_XVI", "id": 10172108}, {"name": "Nobles_italianas_del_siglo_XIII", "id": 10177135}, {"name": "Princesas_de_Alemania", "id": 7823446}, {"name": "Condesas_de_Alemania", "id": 8162557}, {"name": "Nobles_alemanas_del_siglo_XVII", "id": 10369778}, {"name": "Nobles_alemanas_del_siglo_XVIII", "id": 10369781}, {"name": "Nobles_alemanas_del_siglo_XIX", "id": 10369797}, {"name": "Nobles_alemanas_del_siglo_XVI", "id": 10369810}, {"name": "Duquesas_consortes_de_Alemania_del_siglo_XVII", "id": 10370138}, {"name": "Deportistas_femeninas_de_Alemania", "id": 8693494}, {"name": "Futbolistas_femeninas_de_Alemania", "id": 2077957}, {"name": "Futbolistas_de_la_selección_femenina_de_fútbol_de_Alemania", "id": 9492545}]}