{"name": "Magnitudes_físicas", "id": 79584, "predecessors": [{"name": "Conceptos_fundamentales_de_la_física", "id": 1446427}, {"name": "Física", "id": 50638}, {"name": "Medición", "id": 5060662}], "successors": [{"name": "Energía", "id": 51341}, {"name": "Constantes_físicas", "id": 211349}, {"name": "Tiempo", "id": 211414}, {"name": "Magnitudes_termodinámicas", "id": 1074087}, {"name": "Fuerza", "id": 1850966}, {"name": "Magnitudes_electromagnéticas", "id": 2570228}, {"name": "Magnitudes_meteorológicas,_climatológicas_y_atmosféricas", "id": 3525442}, {"name": "Masa", "id": 4033404}, {"name": "Presión", "id": 4232969}, {"name": "Unidades_de_volumen", "id": 59290}]}