{"name": "Nacidos_en_Estados_Unidos", "id": 9356628, "predecessors": [{"name": "Estadounidenses", "id": 173348}, {"name": "Personalidad", "id": 4496858}], "successors": [{"name": "Nacidos_en_New_Haven_(Connecticut)", "id": 7081359}, {"name": "Nacidos_en_Madison_(Wisconsin)", "id": 9346427}, {"name": "Nacidos_en_Chicago", "id": 9356616}, {"name": "Nacidos_en_Cincinnati", "id": 9360650}, {"name": "Nacidos_en_San_Luis_(Misuri)", "id": 9360673}, {"name": "Nacidos_en_Kansas_City_(Misuri)", "id": 9360728}, {"name": "Nacidos_en_Columbus_(Ohio)", "id": 9360812}, {"name": "Nacidos_en_Filadelfia", "id": 9360838}, {"name": "Nacidos_en_Harrisburg", "id": 9360899}, {"name": "Nacidos_en_Springfield_(Illinois)", "id": 9386279}, {"name": "Nacidos_en_Atlanta", "id": 9386387}, {"name": "Nacidos_en_Trenton", "id": 9386427}, {"name": "Nacidos_en_Elizabeth_(Nueva_Jersey)", "id": 9386444}, {"name": "Nacidos_en_Omaha", "id": 9387161}, {"name": "Nacidos_en_Portland", "id": 9390258}, {"name": "Nacidos_en_Nueva_Orleans", "id": 9392249}, {"name": "Nacidos_en_Baltimore", "id": 9392536}, {"name": "Nacidos_en_Albany", "id": 9392584}, {"name": "Nacidos_en_Búfalo", "id": 9392585}, {"name": "Nacidos_en_Savannah", "id": 9394112}, {"name": "Nacidos_en_Mobile", "id": 9394123}, {"name": "Nacidos_en_Montgomery_(Alabama)", "id": 9394125}, {"name": "Nacidos_en_Jackson_(Misisipi)", "id": 9394133}, {"name": "Nacidos_en_Salt_Lake_City", "id": 9461372}, {"name": "Nacidos_en_Tulsa", "id": 9463756}, {"name": "Nacidos_en_Oklahoma_City", "id": 9463760}, {"name": "Nacidos_en_Baton_Rouge", "id": 9473570}, {"name": "Nacidos_en_Shreveport", "id": 9473571}, {"name": "Nacidos_en_Seattle", "id": 9492240}, {"name": "Nacidos_en_Spokane_(Washington)", "id": 9536788}, {"name": "Nacidos_en_Des_Moines", "id": 9667675}, {"name": "Nacidos_en_Phoenix", "id": 9682605}, {"name": "Nacidos_en_Tucson", "id": 9683388}, {"name": "Nacidos_en_Boston", "id": 9829717}, {"name": "Nacidos_en_Honolulu", "id": 9904146}, {"name": "Nacidos_en_Nueva_York", "id": 9919184}, {"name": "Nacidos_en_San_José_(California)", "id": 9943178}, {"name": "Nacidos_en_Newport_Beach", "id": 9949070}, {"name": "Nacidos_en_Indianápolis", "id": 9953199}, {"name": "Nacidos_en_Wichita", "id": 9978206}, {"name": "Nacidos_en_Detroit", "id": 10086000}, {"name": "Nacidos_en_Hartford", "id": 10291474}, {"name": "Nacidos_en_Little_Rock_(Arkansas)", "id": 10348822}, {"name": "Nacidos_en_Lincoln_(Nebraska)", "id": 10437385}, {"name": "Nacidos_en_Providence_(Rhode_Island)", "id": 10439440}]}